streamer/__init__.py
streamer/__main__.py
streamer/streamer_client.py
streamer/streamer_core.py
streamer/streamer_server.py
firecrest_streamer-0.0.21.dist-info/METADATA
firecrest_streamer-0.0.21.dist-info/WHEEL
firecrest_streamer-0.0.21.dist-info/entry_points.txt
firecrest_streamer-0.0.21.dist-info/RECORD
