Metadata-Version: 2.4
Name: firecrest-streamer
Version: 0.0.21
Summary: A simple file streamer over websockets.
Project-URL: Homepage, https://github.com/eth-cscs/firecrest-v2
Project-URL: Issues, https://github.com/eth-cscs/firecrest-v2/issues
Author-email: Elia Palme <elia.palme@cscs.ch>
Maintainer-email: Elia Palme <elia.palme@cscs.ch>, Eirini Koutsaniti <eirini.koutsaniti@cscs.ch>
License-Expression: BSD-3-Clause
Classifier: Operating System :: OS Independent
Classifier: Programming Language :: Python :: 3
Requires-Python: >=3.8
Requires-Dist: asyncio
Requires-Dist: click
Requires-Dist: websockets
